{
  "mediaAppearances": [
    {
      "title": "THOR Financial CIO offers a pair of systematic ETFs for a volatile market",
      "outlet": "InvestmentNews",
      "type": "video",
      "date": "2025-06-24",
      "url": "https://www.investmentnews.com/videos/in-the-nasdaq/thor-financial-cio-offers-a-pair-of-systematic-etfs-for-a-volatile-market/261049",
      "description": "Brad Roth sits down with InvestmentNews to highlight the systematic approach of THOR ETFs in a volatile market."
    },
    {
      "title": "Investment Strategies for the Modern Market",
      "outlet": "Zephyr - Adjusted for Risk Podcast",
      "type": "video",
      "date": "2025-06-23",
      "url": "https://www.youtube.com/watch?v=2UGpPVGcKBQ",
      "description": "Brad Roth discusses investment strategies with Ryan Nauman of Zephyr."
    },
    {
      "title": "ETF 360: Brad Roth of THOR Funds discusses THLV and THIR",
      "outlet": "ETF.com",
      "type": "video",
      "date": "2025-05-01",
      "url": "https://www.youtube.com/watch?v=VMyrCjFoDtQ",
      "description": "In-depth discussion of both THOR ETF strategies."
    },
    {
      "title": "Behind the Ticker Podcast Launches on ETF.com",
      "outlet": "Yahoo Finance / Business Wire",
      "type": "article",
      "date": "2026-01-15",
      "url": "https://finance.yahoo.com/news/thor-financial-technologies-brad-roth-130000403.html",
      "description": "Announcement of Behind the Ticker podcast launching on ETF.com."
    },
    {
      "title": "Thor Financial Technologies: Using Smart Algorithms to Tackle Market Volatility",
      "outlet": "FinTech TV",
      "type": "video",
      "date": "2024-10-09",
      "url": "https://fintech.tv/thor-financial-technologies-using-smart-algorithms-to-tackle-market-volatility-with-brad-roth-founder-cio-thor-financial-technologies/",
      "description": "Live at NYSE discussing algorithmic strategies for managing market volatility."
    },
    {
      "title": "Schwab Network's The Watch List - Market Breadth Expanding",
      "outlet": "Schwab Network",
      "type": "video",
      "date": "2024-10-09",
      "url": "https://schwabnetwork.com/video/market-breadth-expanding-beyond-the-mag-7",
      "description": "Discussion on market breadth widening beyond the Magnificent 7."
    },
    {
      "title": "Rotation Out of Large Caps Healthy; Tech Reached Its Limit For Now",
      "outlet": "Schwab Network",
      "type": "video",
      "date": "2024-10-08",
      "url": "https://schwabnetwork.com/video/roth-rotation-out-of-large-caps-healthy-tech-reached-its-limit-for-now",
      "description": "Brad discusses rotation out of large caps and tech limits."
    },
    {
      "title": "Risk Management Strategies: Hard Assets and Low-Volatility ETFs",
      "outlet": "Schwab Network",
      "type": "video",
      "date": "2022-04-20",
      "url": "https://schwabnetwork.com/video/risk-management-strategies-hard-assets-and-low-volatility-etfs",
      "description": "Discussion on value investing, commodities, and hard assets for portfolio hedging."
    },
    {
      "title": "ETF Leaders: Brad Roth at Exchange 2023",
      "outlet": "NYSE / ETF Leaders",
      "type": "video",
      "date": "2023-04-05",
      "url": "https://www.youtube.com/watch?v=nuAF3r73nIc",
      "description": "NYSE's Judy Shaw interviews Brad Roth at Exchange 2023 conference."
    },
    {
      "title": "What's the Fund?: THOR Low Volatility ETF",
      "outlet": "What's the Fund?",
      "type": "video",
      "date": "2023-02-04",
      "url": "https://www.youtube.com/watch?v=DxATMMej8b8",
      "description": "Deep dive into the THOR Low Volatility ETF strategy."
    },
    {
      "title": "THOR Debuts With Volatility-Focused ETF",
      "outlet": "ETF.com / Yahoo Finance",
      "type": "article",
      "date": "2022-09-13",
      "url": "https://www.yahoo.com/video/thor-debuts-volatility-focused-etf-211500350.html",
      "description": "Launch coverage of THLV ETF."
    },
    {
      "title": "Fintech Luminaries - Meet Brad Roth of THOR Financial Technologies",
      "outlet": "DWealth News",
      "type": "article",
      "date": "2021-11-22",
      "url": "https://dwealth.news/2021/11/fintech-luminaries-meet-brad-roth-of-thor-financial-technologies/",
      "description": "Profile feature on Brad Roth and THOR's mission."
    },
    {
      "title": "Trading 360",
      "outlet": "YouTube",
      "type": "video",
      "date": "2024",
      "url": "https://www.youtube.com/watch?v=H6-nyqtEmCs",
      "description": "Trading and market discussion."
    }
  ]
}
